measurenary/__init__.py
measurenary/agglomerative_best.py
measurenary/distance.py
measurenary/pair_best.py
measurenary/similarity.py
measurenary/utility.py
measurenary-1.0.4.dist-info/LICENSE
measurenary-1.0.4.dist-info/METADATA
measurenary-1.0.4.dist-info/WHEEL
measurenary-1.0.4.dist-info/top_level.txt
measurenary-1.0.4.dist-info/RECORD
