Metadata-Version: 2.1
Name: measurenary
Version: 1.0.4
Summary: A package to calculate and find the best similarity between binary data features
Home-page: https://measurenary.readthedocs.io/en/latest/
Author: Muhammad Dwiki Ramdhani
Author-email: Muhammad Dwiki Ramdhani <mdramdha@gmail.com>
Project-URL: Homepage, https://github.com/dwikiramdhani53/measurenary
Classifier: Programming Language :: Python :: 3
Classifier: License :: OSI Approved :: BSD License
Classifier: Operating System :: OS Independent
Requires-Python: >=3.6
License-File: LICENSE
Requires-Dist: numpy (>=1.21.6)
Requires-Dist: pandas (>=1.3.5)
Requires-Dist: scikit-learn
Requires-Dist: setuptools (>=42)
Requires-Dist: tqdm
